pymicrohttp/__init__.py
pymicrohttp/path_matching.py
pymicrohttp/server.py
pymicrohttp-0.1.3.dist-info/LICENSE
pymicrohttp-0.1.3.dist-info/METADATA
pymicrohttp-0.1.3.dist-info/WHEEL
pymicrohttp-0.1.3.dist-info/top_level.txt
pymicrohttp-0.1.3.dist-info/RECORD
