Metadata-Version: 2.1
Name: pymicrohttp
Version: 0.1.3
Summary: Tiny lightweight, flexible HTTP framework.
Home-page: https://github.com/hasssanezzz/PyMicroHTTP
Author: Hassan Ezz
Author-email: dhassanezz@gmail.com
Classifier: Programming Language :: Python :: 3
Classifier: Operating System :: OS Independent
Requires-Python: >=3.6
License-File: LICENSE
